primenumscalc/__init__.py
primenumscalc-1.1.dist-info/LICENSE.txt
primenumscalc-1.1.dist-info/METADATA
primenumscalc-1.1.dist-info/WHEEL
primenumscalc-1.1.dist-info/top_level.txt
primenumscalc-1.1.dist-info/RECORD
