Metadata-Version: 2.1
Name: primenumscalc
Version: 1.1
Summary: A tool to calculate and list prime numbers.
Home-page: UNKNOWN
Author: Sebastián Mosca
Author-email: sebasmca@gmail.com
License: GNU GPLv3
Keywords: prime numbers calculator
Platform: UNKNOWN
Classifier: Development Status :: 4 - Beta
Classifier: Intended Audience :: Developers
Classifier: Topic :: Utilities
Classifier: License :: OSI Approved :: GNU General Public License v3 (GPLv3)
Classifier: Programming Language :: Python :: 3
Classifier: Operating System :: OS Independent
License-File: LICENSE.txt
